setup.cfg
setup.py
virtstrap_bundler_and_npm/__init__.py
virtstrap_bundler_and_npm/plugin.py
virtstrap_bundler_and_npm.egg-info/PKG-INFO
virtstrap_bundler_and_npm.egg-info/SOURCES.txt
virtstrap_bundler_and_npm.egg-info/dependency_links.txt
virtstrap_bundler_and_npm.egg-info/entry_points.txt
virtstrap_bundler_and_npm.egg-info/not-zip-safe
virtstrap_bundler_and_npm.egg-info/requires.txt
virtstrap_bundler_and_npm.egg-info/top_level.txt