Metadata-Version: 1.0
Name: virtstrap-bundler-and-npm
Version: 0.0.1
Summary: A virtstrap plugin that installs bundler Gemfiles and nodejs local dependencies
Home-page: UNKNOWN
Author: Mattias Wong
Author-email: 0x1998@gmail.com
License: MIT
Keywords: virtstrap ruby bundler nodejs npm virtualenv pip
Platform: UNKNOWN
